koma-0.1.1.dist-info/METADATA
koma-0.1.1.dist-info/WHEEL
koma/__init__.py
koma/core/__init__.py
koma/core/model.py
koma/core/render.py
koma/domain/__init__.py
koma/domain/models/__init__.py
koma/domain/models/attachment.py
koma/domain/models/note.py
koma/domain/models/style.py
koma/infra/__init__.py
koma/infra/fetchers/__init__.py
koma/infra/fetchers/apple.py
koma/infra/fetchers/base.py
koma/infra/helper/__init__.py
koma/infra/helper/apple.py
koma/infra/renderers/__init__.py
koma/infra/renderers/base.py
koma/infra/renderers/markdown.py
koma/protobuf/__init__.py
koma/protobuf/notestore_pb2.py
koma/protobuf/notestore_pb2.pyi
koma-0.1.1.dist-info/RECORD
