Metadata-Version: 2.1
Name: koma
Version: 0.1.1
Summary: The knowledge of macOS for AI.
Author-Email: AFuture <afuture.d@outlook.com>
License: MIT
Requires-Python: >=3.12
Requires-Dist: protobuf>=5.26.1
Requires-Dist: pydantic>=2.7.3
